<?xml version="1.0" encoding="utf-8"?>
<templates xml:space="preserve">
     <t t-name="button_estate.FormView.Buttons" t-inherit="web.FormView">
      <xpath expr="//t[@t-set-slot='layout-buttons']" position="inside">
           <button type="button" class="btn btn-outline-success"
               t-on-click="OnSaveItem" context="resId:2">
               <span>Save</span>
           </button>
           <button type="button" class="btn btn-outline-danger"
               t-on-click="OnDeleteItem">
               <span>Delete</span>
           </button>
       </xpath>
   </t>
</templates>